pyoneering/__init__.py
pyoneering/core.py
pyoneering/devutils.py
pyoneering/presets.py
pyoneering-0.1.0.dist-info/AUTHORS.rst
pyoneering-0.1.0.dist-info/LICENSE
pyoneering-0.1.0.dist-info/METADATA
pyoneering-0.1.0.dist-info/WHEEL
pyoneering-0.1.0.dist-info/top_level.txt
pyoneering-0.1.0.dist-info/RECORD
